backupdirsm/__init__.py
backupdirsm/main.py
backupdirsm-0.0.8.dist-info/LICENSE
backupdirsm-0.0.8.dist-info/METADATA
backupdirsm-0.0.8.dist-info/WHEEL
backupdirsm-0.0.8.dist-info/entry_points.txt
backupdirsm-0.0.8.dist-info/RECORD
